pyroborock/__init__.py
pyroborock_grizmin-1.0.10.dist-info/METADATA
pyroborock_grizmin-1.0.10.dist-info/WHEEL
pyroborock_grizmin-1.0.10.dist-info/top_level.txt
pyroborock_grizmin-1.0.10.dist-info/RECORD
