Metadata-Version: 2.1
Name: pyroborock-grizmin
Version: 1.0.10
Summary: Communicate with roborock over tuya protocol
Home-page: https://github.com/grizmin/pyroborock
Author: jd89
Author-email: jd89.dev@gmail.com
Requires-Dist: pytuyapi-ipc
Requires-Dist: python-miio
Requires-Dist: pycryptodome
